{
"71ab9546-5534-83f1-898e-87f4d97957b4": {
"DB III (EUR)": "if(empty(prop(\"Formel DB II ( Eur )\")) or empty(prop(\"GK Kosten (EUR)\")),\n  \"€0.00\",\n  /* Calculate DB III and format with EUR symbol */\n  \"€\" + format(round(prop(\"Formel DB II ( Eur )\") - prop(\"GK Kosten (EUR)\"), 2))\n)",
"Formel Umsatz Gesamt Netto": "if(empty(prop(\"Umsatz Gesamt Netto\")), 0,\n  /* Remove all characters except numbers, decimal points, commas, and minus */\n  toNumber(\n    prop(\"Umsatz Gesamt Netto\")\n      .replaceAll(\"[^0-9.,-]\", \"\")\n      /* Replace comma with period for decimal point */\n      .replaceAll(\",\", \".\")\n  )\n)",
"Ø Umsatz Brutto pro Tag": "if(empty(prop(\"Öffnungstage\")) or prop(\"Öffnungstage\") == 0,\n  \"0,00 €\",\n  /* Calculate average and format as EUR */\n  format(round(prop(\"Formel Umsatz Gesamt Brutto\") / prop(\"Öffnungstage\"), 2)) + \" €\"\n)",
"Formel Durchschnittsbon": "if(empty(prop(\"Durchschnittsbon (EUR)\")),\n  0,\n  toNumber(prop(\"Durchschnittsbon (EUR)\"))\n)",
"Formel DB I (%)": "if(empty(prop(\"DB I (%)\")), 0,\n  /* Remove all characters except numbers, decimal points, commas, and minus */\n  toNumber(\n    prop(\"DB I (%)\")\n      .replaceAll(\"[^0-9.,-]\", \"\")\n      /* Replace comma with period for decimal point */\n      .replaceAll(\",\", \".\")\n  )\n)",
"Formel Personalkosten ( Eur )": "if(empty(prop(\"Personalkosten\")), 0,\n  /* Remove all characters except numbers, decimal points, commas, and minus */\n  toNumber(\n    prop(\"Personalkosten\")\n      .replaceAll(\"[^0-9.,-]\", \"\")\n      /* Replace comma with period for decimal point */\n      .replaceAll(\",\", \".\")\n  )\n)",
"Formel Produktivität / H": "if(empty(prop(\"Produktivität (EUR/h)\")), 0,\n  /* Remove all characters except numbers, decimal points, commas, and minus */\n  toNumber(\n    prop(\"Produktivität (EUR/h)\")\n      .replaceAll(\"[^0-9.,-]\", \"\")\n      /* Replace comma with period for decimal point */\n      .replaceAll(\",\", \".\")\n  )\n)",
"Formel Personaleinsatz ( % )": "if(empty(prop(\"Personaleinsatz (%)\")), 0,\n  /* Remove all non-numeric characters and convert to number */\n  toNumber(\n    prop(\"Personaleinsatz (%)\")\n      /* Keep only numbers, decimal points, commas, and minus signs */\n      .replaceAll(\"[^0-9.,-]\", \"\")\n      /* Replace comma with period for decimal point */\n      .replaceAll(\",\", \".\")\n  )\n)",
"DB I (EUR)": "if(empty(prop(\"Umsatz Gesamt Netto\")) or empty(prop(\"Wareneinsatz (EUR)\")),\n  \"€0.00\",\n  /* Calculate DB I as revenue minus cost of goods */\n  \"€\" + format(round(toNumber(prop(\"Umsatz Gesamt Netto\")) - prop(\"Wareneinsatz (EUR)\"), 2))\n)",
"Durchschnittsbon (EUR)": "if(empty(prop(\"Anzahl Transaktionen\")) or prop(\"Anzahl Transaktionen\") == 0,\n  \"0.00\",\n  if(empty(prop(\"Formel Umsatz Gesamt Netto\")),\n    \"0.00\",\n    /* Calculate average transaction value */\n    format(round(prop(\"Formel Umsatz Gesamt Netto\") / prop(\"Anzahl Transaktionen\"), 2))\n  )\n)",
"DB I (%)": "lets(\n  /* Clean and convert text properties to numbers by removing non-numeric characters */\n  dbOne, toNumber(prop(\"DB I (EUR)\").replaceAll(\"[^0-9.-]\", \"\")),\n  umsatzGesamt, toNumber(prop(\"Umsatz Gesamt Netto\").replaceAll(\"[^0-9.-]\", \"\")),\n  /* Calculate and return percentage */\n  if(dbOne == 0 and umsatzGesamt == 0,\n    \"0.0%\",\n    if(umsatzGesamt == 0,\n      \"N/A\",\n      format(round(dbOne / umsatzGesamt * 100, 1)) + \"%\"\n    )\n  )\n)",
"Formel DB II (%)": "if(empty(prop(\"DB II (%)\")), 0,\n  /* Remove all characters except numbers, decimal points, commas, and minus */\n  toNumber(\n    prop(\"DB II (%)\")\n      .replaceAll(\"[^0-9.,-]\", \"\")\n      /* Replace comma with period for decimal point */\n      .replaceAll(\",\", \".\")\n  )\n)",
"DB II (EUR)": "lets(\n  /* Extract numeric value from DB I text by removing currency symbols and converting */\n  dbValue, toNumber(prop(\"DB I (EUR)\").replaceAll(\"[^0-9.-]\", \"\")),\n  /* Extract numeric value from personnel costs */\n  personalValue, toNumber(prop(\"Personalkosten\").replaceAll(\"[^0-9.-]\", \"\")),\n  /* Return result with proper formatting */\n  if(empty(prop(\"DB I (EUR)\")) or empty(prop(\"Personalkosten\")) or dbValue == 0 or personalValue == 0,\n    \"—\",\n    \"€\" + format(round(dbValue - personalValue, 2))\n  )\n)",
"Formel WE ( % )": "if(empty(prop(\"Wareneinsatz (%)\")), 0,\n  /* Remove all characters except numbers, decimal points, commas, and minus */\n  toNumber(\n    prop(\"Wareneinsatz (%)\")\n      .replaceAll(\"[^0-9.,-]\", \"\")\n      /* Replace comma with period for decimal point */\n      .replaceAll(\",\", \".\")\n  )\n)",
"Umsatz Gesamt Brutto": "if(empty(prop(\"Umsatz Gesamt Netto\")),\n  \"€0.00\",\n  /* Convert net revenue to number, multiply by 1.19 for VAT, and format */\n  \"€\" + format(round(toNumber(prop(\"Umsatz Gesamt Netto\")) * 1.19, 2))\n)",
"Formel Umsatz Gesamt Brutto": "if(empty(prop(\"Umsatz Gesamt Brutto\")), 0,\n  /* Remove currency symbols and convert to number */\n  toNumber(\n    prop(\"Umsatz Gesamt Brutto\")\n    /* Keep only numbers, decimal points, commas, and minus */\n    .replaceAll(\"[^0-9.,-]\", \"\")\n    /* Replace comma with period for decimal point */\n    .replaceAll(\",\", \".\")\n  )\n)",
"Formel DB III (%)": "prop(\"DB III (%)\")",
"Umsatz Gesamt Netto": "/* Sum all revenue sources and format as EUR */\nformat(\n  round(\n    (if(empty(prop(\"Umsatz Netto Store Exkl. Trinkgeld\")), 0, prop(\"Umsatz Netto Store Exkl. Trinkgeld\")) +\n    if(empty(prop(\"Umsatz Lieferando\")), 0, prop(\"Umsatz Lieferando\")) +\n    if(empty(prop(\"Umsatz Wolt\")), 0, prop(\"Umsatz Wolt\"))),\n    2\n  )\n) + \" EUR\"",
"DB II (%)": "lets(\n  /* Clean and convert text properties to numbers by removing non-numeric characters */\n  dbTwo, toNumber(prop(\"DB II (EUR)\").replaceAll(\"[^0-9.-]\", \"\")),\n  umsatzGesamt, toNumber(prop(\"Umsatz Gesamt Netto\").replaceAll(\"[^0-9.-]\", \"\")),\n  /* Calculate and return percentage */\n  if(dbTwo == 0 and umsatzGesamt == 0,\n    \"0.0%\",\n    if(umsatzGesamt == 0,\n      \"N/A\",\n      format(round(dbTwo / umsatzGesamt * 100, 1)) + \"%\"\n    )\n  )\n)",
"Wareneinsatz (%)": "lets(\n  /* Convert text revenue to number for calculation */\n  umsatzGesamt, toNumber(prop(\"Umsatz Gesamt Netto\")),\n  /* Return appropriate result based on data availability */\n  ifs(\n    empty(prop(\"Umsatz Gesamt Netto\")) or empty(umsatzGesamt) or umsatzGesamt == 0, \"N/A\",\n    empty(prop(\"Wareneinsatz (EUR)\")), \"0.0%\",\n    format(round(prop(\"Wareneinsatz (EUR)\") / umsatzGesamt * 100, 1)) + \"%\"\n  )\n)",
"Formel GK Kosten ( Eur )": "if(empty(prop(\"GK Kosten (EUR)\")), 0,\n  /* Remove all characters except numbers, decimal points, commas, and minus */\n  toNumber(\n    format(prop(\"GK Kosten (EUR)\"))\n      .replaceAll(\"[^0-9.,-]\", \"\")\n      /* Replace comma with period for decimal point */\n      .replaceAll(\",\", \".\")\n  )\n)",
"Formel DB I (EUR)": "if(empty(prop(\"DB I (EUR)\")), 0,\n  /* Remove all characters except numbers, decimal points, commas, and minus */\n  toNumber(\n    prop(\"DB I (EUR)\")\n      .replaceAll(\"[^0-9.,-]\", \"\")\n      /* Replace comma with period for decimal point */\n      .replaceAll(\",\", \".\")\n  )\n)",
"Formel DB II ( Eur )": "if(empty(prop(\"DB II (EUR)\")),\n  0,\n  /* Remove all characters except numbers, decimal points, commas, and minus */\n  toNumber(\n    prop(\"DB II (EUR)\")\n      .replaceAll(\"[^0-9.,-]\", \"\")\n      /* Replace comma with period for decimal point */\n      .replaceAll(\",\", \".\")\n  )\n)",
"DB III (%)": "lets(\n  /* Clean and convert text properties to numbers by removing non-numeric characters */\n  dbThree, toNumber(prop(\"DB III (EUR)\").replaceAll(\"[^0-9.-]\", \"\")),\n  umsatzGesamt, toNumber(prop(\"Umsatz Gesamt Netto\").replaceAll(\"[^0-9.-]\", \"\")),\n  /* Calculate and return percentage */\n  if(dbThree == 0 and umsatzGesamt == 0,\n    \"0.0%\",\n    if(umsatzGesamt == 0,\n      \"N/A\",\n      format(round(dbThree / umsatzGesamt * 100, 1)) + \"%\"\n    )\n  )\n)",
"Produktivität (EUR/h)": "if(empty(prop(\"Geleistete Stunden\")) or prop(\"Geleistete Stunden\") == 0,\n  \"N/A\",\n  if(empty(prop(\"Umsatz Gesamt Netto\")),\n    \"N/A\",\n    /* Convert text revenue to number and calculate per hour */\n    \"€\" + format(round(toNumber(prop(\"Umsatz Gesamt Netto\")) / prop(\"Geleistete Stunden\"), 2))\n  )\n)",
"Personaleinsatz (%)": "if(\n  empty(prop(\"Formel Umsatz Gesamt Netto\")) or prop(\"Formel Umsatz Gesamt Netto\") == 0,\n  \"0%\",\n  /* Calculate percentage and format with % sign */\n  format(round(\n    prop(\"Formel Personalkosten ( Eur )\") / prop(\"Formel Umsatz Gesamt Netto\") * 100.2,\n    2\n  )) + \"%\"\n)",
"Formel DB III (EUR)": "if(empty(prop(\"DB III (EUR)\")), 0,\n  /* Remove currency symbols and spaces, keep only numbers and decimal separators */\n  toNumber(\n    prop(\"DB III (EUR)\")\n      .replaceAll(\"[^0-9.,-]\", \"\")\n      /* Replace comma with period for decimal point */\n      .replaceAll(\",\", \".\")\n  )\n)",
"Ø Umsatz Netto pro Tag": "lets(\n  /* Convert text revenue to number for calculation */\n  revenueNumber, toNumber(prop(\"Umsatz Gesamt Netto\")),\n  openDays, prop(\"Öffnungstage\"),\n  /* Return appropriate result */\n  if(empty(revenueNumber) or empty(openDays) or openDays == 0,\n    \"€0.00\",\n    /* Calculate average revenue per day */\n    \"€\" + format(round(revenueNumber / openDays, 2))\n  )\n)"
}
}